{
  "openapi": "3.0.1",
  "info": {
    "title": "Unit Converter API",
    "description": "API RESTful para conversión de unidades entre diferentes sistemas de medida",
    "contact": {
      "name": "Equipo de Desarrollo",
      "email": "dev@unitconverter.com"
    },
    "license": {
      "name": "MIT License"
    },
    "version": "v1.0"
  },
  "paths": {
    "/api/Conversion/centimetros-a-metros": {
      "post": {
        "tags": [
          "Conversion"
        ],
        "requestBody": {
          "content": {
            "application/json": {
              "schema": {
                "type": "number",
                "format": "double"
              }
            },
            "text/json": {
              "schema": {
                "type": "number",
                "format": "double"
              }
            },
            "application/*+json": {
              "schema": {
                "type": "number",
                "format": "double"
              }
            }
          }
        },
        "responses": {
          "200": {
            "description": "OK",
            "content": {
              "text/plain": {
                "schema": {
                  "$ref": "#/components/schemas/DoubleApiResponse"
                }
              },
              "application/json": {
                "schema": {
                  "$ref": "#/components/schemas/DoubleApiResponse"
                }
              },
              "text/json": {
                "schema": {
                  "$ref": "#/components/schemas/DoubleApiResponse"
                }
              }
            }
          }
        }
      }
    },
    "/api/Conversion/metros-a-centimetros": {
      "post": {
        "tags": [
          "Conversion"
        ],
        "requestBody": {
          "content": {
            "application/json": {
              "schema": {
                "type": "number",
                "format": "double"
              }
            },
            "text/json": {
              "schema": {
                "type": "number",
                "format": "double"
              }
            },
            "application/*+json": {
              "schema": {
                "type": "number",
                "format": "double"
              }
            }
          }
        },
        "responses": {
          "200": {
            "description": "OK",
            "content": {
              "text/plain": {
                "schema": {
                  "$ref": "#/components/schemas/DoubleApiResponse"
                }
              },
              "application/json": {
                "schema": {
                  "$ref": "#/components/schemas/DoubleApiResponse"
                }
              },
              "text/json": {
                "schema": {
                  "$ref": "#/components/schemas/DoubleApiResponse"
                }
              }
            }
          }
        }
      }
    },
    "/api/Conversion/metros-a-kilometros": {
      "post": {
        "tags": [
          "Conversion"
        ],
        "requestBody": {
          "content": {
            "application/json": {
              "schema": {
                "type": "number",
                "format": "double"
              }
            },
            "text/json": {
              "schema": {
                "type": "number",
                "format": "double"
              }
            },
            "application/*+json": {
              "schema": {
                "type": "number",
                "format": "double"
              }
            }
          }
        },
        "responses": {
          "200": {
            "description": "OK",
            "content": {
              "text/plain": {
                "schema": {
                  "$ref": "#/components/schemas/DoubleApiResponse"
                }
              },
              "application/json": {
                "schema": {
                  "$ref": "#/components/schemas/DoubleApiResponse"
                }
              },
              "text/json": {
                "schema": {
                  "$ref": "#/components/schemas/DoubleApiResponse"
                }
              }
            }
          }
        }
      }
    },
    "/api/Conversion/tonelada-a-libra": {
      "post": {
        "tags": [
          "Conversion"
        ],
        "requestBody": {
          "content": {
            "application/json": {
              "schema": {
                "type": "number",
                "format": "double"
              }
            },
            "text/json": {
              "schema": {
                "type": "number",
                "format": "double"
              }
            },
            "application/*+json": {
              "schema": {
                "type": "number",
                "format": "double"
              }
            }
          }
        },
        "responses": {
          "200": {
            "description": "OK",
            "content": {
              "text/plain": {
                "schema": {
                  "$ref": "#/components/schemas/DoubleApiResponse"
                }
              },
              "application/json": {
                "schema": {
                  "$ref": "#/components/schemas/DoubleApiResponse"
                }
              },
              "text/json": {
                "schema": {
                  "$ref": "#/components/schemas/DoubleApiResponse"
                }
              }
            }
          }
        }
      }
    },
    "/api/Conversion/kilogramo-a-libra": {
      "post": {
        "tags": [
          "Conversion"
        ],
        "requestBody": {
          "content": {
            "application/json": {
              "schema": {
                "type": "number",
                "format": "double"
              }
            },
            "text/json": {
              "schema": {
                "type": "number",
                "format": "double"
              }
            },
            "application/*+json": {
              "schema": {
                "type": "number",
                "format": "double"
              }
            }
          }
        },
        "responses": {
          "200": {
            "description": "OK",
            "content": {
              "text/plain": {
                "schema": {
                  "$ref": "#/components/schemas/DoubleApiResponse"
                }
              },
              "application/json": {
                "schema": {
                  "$ref": "#/components/schemas/DoubleApiResponse"
                }
              },
              "text/json": {
                "schema": {
                  "$ref": "#/components/schemas/DoubleApiResponse"
                }
              }
            }
          }
        }
      }
    },
    "/api/Conversion/gramo-a-kilogramo": {
      "post": {
        "tags": [
          "Conversion"
        ],
        "requestBody": {
          "content": {
            "application/json": {
              "schema": {
                "type": "number",
                "format": "double"
              }
            },
            "text/json": {
              "schema": {
                "type": "number",
                "format": "double"
              }
            },
            "application/*+json": {
              "schema": {
                "type": "number",
                "format": "double"
              }
            }
          }
        },
        "responses": {
          "200": {
            "description": "OK",
            "content": {
              "text/plain": {
                "schema": {
                  "$ref": "#/components/schemas/DoubleApiResponse"
                }
              },
              "application/json": {
                "schema": {
                  "$ref": "#/components/schemas/DoubleApiResponse"
                }
              },
              "text/json": {
                "schema": {
                  "$ref": "#/components/schemas/DoubleApiResponse"
                }
              }
            }
          }
        }
      }
    },
    "/api/Conversion/celsius-a-fahrenheit": {
      "post": {
        "tags": [
          "Conversion"
        ],
        "requestBody": {
          "content": {
            "application/json": {
              "schema": {
                "type": "number",
                "format": "double"
              }
            },
            "text/json": {
              "schema": {
                "type": "number",
                "format": "double"
              }
            },
            "application/*+json": {
              "schema": {
                "type": "number",
                "format": "double"
              }
            }
          }
        },
        "responses": {
          "200": {
            "description": "OK",
            "content": {
              "text/plain": {
                "schema": {
                  "$ref": "#/components/schemas/DoubleApiResponse"
                }
              },
              "application/json": {
                "schema": {
                  "$ref": "#/components/schemas/DoubleApiResponse"
                }
              },
              "text/json": {
                "schema": {
                  "$ref": "#/components/schemas/DoubleApiResponse"
                }
              }
            }
          }
        }
      }
    },
    "/api/Conversion/fahrenheit-a-celsius": {
      "post": {
        "tags": [
          "Conversion"
        ],
        "requestBody": {
          "content": {
            "application/json": {
              "schema": {
                "type": "number",
                "format": "double"
              }
            },
            "text/json": {
              "schema": {
                "type": "number",
                "format": "double"
              }
            },
            "application/*+json": {
              "schema": {
                "type": "number",
                "format": "double"
              }
            }
          }
        },
        "responses": {
          "200": {
            "description": "OK",
            "content": {
              "text/plain": {
                "schema": {
                  "$ref": "#/components/schemas/DoubleApiResponse"
                }
              },
              "application/json": {
                "schema": {
                  "$ref": "#/components/schemas/DoubleApiResponse"
                }
              },
              "text/json": {
                "schema": {
                  "$ref": "#/components/schemas/DoubleApiResponse"
                }
              }
            }
          }
        }
      }
    },
    "/api/Conversion/celsius-a-kelvin": {
      "post": {
        "tags": [
          "Conversion"
        ],
        "requestBody": {
          "content": {
            "application/json": {
              "schema": {
                "type": "number",
                "format": "double"
              }
            },
            "text/json": {
              "schema": {
                "type": "number",
                "format": "double"
              }
            },
            "application/*+json": {
              "schema": {
                "type": "number",
                "format": "double"
              }
            }
          }
        },
        "responses": {
          "200": {
            "description": "OK",
            "content": {
              "text/plain": {
                "schema": {
                  "$ref": "#/components/schemas/DoubleApiResponse"
                }
              },
              "application/json": {
                "schema": {
                  "$ref": "#/components/schemas/DoubleApiResponse"
                }
              },
              "text/json": {
                "schema": {
                  "$ref": "#/components/schemas/DoubleApiResponse"
                }
              }
            }
          }
        }
      }
    },
    "/api/Conversion/health": {
      "get": {
        "tags": [
          "Conversion"
        ],
        "responses": {
          "200": {
            "description": "OK",
            "content": {
              "text/plain": {
                "schema": {
                  "$ref": "#/components/schemas/StringApiResponse"
                }
              },
              "application/json": {
                "schema": {
                  "$ref": "#/components/schemas/StringApiResponse"
                }
              },
              "text/json": {
                "schema": {
                  "$ref": "#/components/schemas/StringApiResponse"
                }
              }
            }
          }
        }
      }
    },
    "/api/Conversion/funciones": {
      "get": {
        "tags": [
          "Conversion"
        ],
        "responses": {
          "200": {
            "description": "OK",
            "content": {
              "text/plain": {
                "schema": {
                  "$ref": "#/components/schemas/StringListApiResponse"
                }
              },
              "application/json": {
                "schema": {
                  "$ref": "#/components/schemas/StringListApiResponse"
                }
              },
              "text/json": {
                "schema": {
                  "$ref": "#/components/schemas/StringListApiResponse"
                }
              }
            }
          }
        }
      }
    },
    "/WeatherForecast": {
      "get": {
        "tags": [
          "WeatherForecast"
        ],
        "operationId": "GetWeatherForecast",
        "responses": {
          "200": {
            "description": "OK",
            "content": {
              "text/plain": {
                "schema": {
                  "type": "array",
                  "items": {
                    "$ref": "#/components/schemas/WeatherForecast"
                  }
                }
              },
              "application/json": {
                "schema": {
                  "type": "array",
                  "items": {
                    "$ref": "#/components/schemas/WeatherForecast"
                  }
                }
              },
              "text/json": {
                "schema": {
                  "type": "array",
                  "items": {
                    "$ref": "#/components/schemas/WeatherForecast"
                  }
                }
              }
            }
          }
        }
      }
    }
  },
  "components": {
    "schemas": {
      "DoubleApiResponse": {
        "type": "object",
        "properties": {
          "success": {
            "type": "boolean"
          },
          "message": {
            "type": "string",
            "nullable": true
          },
          "data": {
            "type": "number",
            "format": "double"
          },
          "timestamp": {
            "type": "string",
            "format": "date-time"
          }
        },
        "additionalProperties": false
      },
      "StringApiResponse": {
        "type": "object",
        "properties": {
          "success": {
            "type": "boolean"
          },
          "message": {
            "type": "string",
            "nullable": true
          },
          "data": {
            "type": "string",
            "nullable": true
          },
          "timestamp": {
            "type": "string",
            "format": "date-time"
          }
        },
        "additionalProperties": false
      },
      "StringListApiResponse": {
        "type": "object",
        "properties": {
          "success": {
            "type": "boolean"
          },
          "message": {
            "type": "string",
            "nullable": true
          },
          "data": {
            "type": "array",
            "items": {
              "type": "string"
            },
            "nullable": true
          },
          "timestamp": {
            "type": "string",
            "format": "date-time"
          }
        },
        "additionalProperties": false
      },
      "WeatherForecast": {
        "type": "object",
        "properties": {
          "date": {
            "type": "string",
            "format": "date"
          },
          "temperatureC": {
            "type": "integer",
            "format": "int32"
          },
          "temperatureF": {
            "type": "integer",
            "format": "int32",
            "readOnly": true
          },
          "summary": {
            "type": "string",
            "nullable": true
          }
        },
        "additionalProperties": false
      }
    }
  }
}